modsdkspring/__init__.py
modsdkspring/constants.py
modsdkspring/main.py
modsdkspring/utils.py
modsdkspring/cli/__init__.py
modsdkspring/cli/commands.py
modsdkspring/cli/import_command.py
modsdkspring/cli/init_command.py
modsdkspring/config/__init__.py
modsdkspring/config/project_config.py
modsdkspring/generators/__init__.py
modsdkspring/generators/project_generator.py
modsdkspring/generators/template_engine.py
modsdkspring/templates/README.md
modsdkspring/templates/configs/manifest_behavior.json
modsdkspring/templates/configs/manifest_resource.json
modsdkspring/templates/framework/CrossEndCommunication/README.md
modsdkspring/templates/framework/CrossEndCommunication/__init__.py
modsdkspring/templates/framework/CrossEndCommunication/core/ClientCommunicator.py
modsdkspring/templates/framework/CrossEndCommunication/core/ServerCommunicator.py
modsdkspring/templates/framework/CrossEndCommunication/core/__init__.py
modsdkspring/templates/framework/GrapeSettings/README.md
modsdkspring/templates/framework/GrapeSettings/__init__.py
modsdkspring/templates/framework/GrapeSettings/config_system.py
modsdkspring/templates/framework/GrapeSettings/constants.py
modsdkspring/templates/framework/GrapeSettings/core/__init__.py
modsdkspring/templates/framework/GrapeSettings/core/client_context.py
modsdkspring/templates/framework/GrapeSettings/core/registry.py
modsdkspring/templates/framework/GrapeSettings/handlers/__init__.py
modsdkspring/templates/framework/GrapeSettings/handlers/event_handler.py
modsdkspring/templates/framework/GrapeSettings/managers/__init__.py
modsdkspring/templates/framework/GrapeSettings/managers/config_manager.py
modsdkspring/templates/framework/GrapeSettings/proxy/__init__.py
modsdkspring/templates/framework/GrapeSettings/proxy/esc_ui_proxy.py
modsdkspring/templates/framework/GrapeSettings/screen/__init__.py
modsdkspring/templates/framework/GrapeSettings/screen/grape_settings_screen.py
modsdkspring/templates/framework/GrapeSettings/ui/__init__.py
mcmod_cli-1.2.2.dist-info/LICENSE
mcmod_cli-1.2.2.dist-info/METADATA
mcmod_cli-1.2.2.dist-info/WHEEL
mcmod_cli-1.2.2.dist-info/entry_points.txt
mcmod_cli-1.2.2.dist-info/top_level.txt
mcmod_cli-1.2.2.dist-info/RECORD
