Metadata-Version: 2.1
Name: mcmod-cli
Version: 1.2.2
Summary: A CLI tool for generating Minecraft Mod project structure and managing MODSDK development.
Home-page: https://github.com/CreatorMC/MODSDKSping
Author: CreatorMC
License: UNKNOWN
Platform: any
Classifier: Programming Language :: Python :: 2.7
Classifier: License :: OSI Approved :: MIT License
